xml_to_df/__init__.py
xml_to_df-0.0.6.dist-info/LICENSE
xml_to_df-0.0.6.dist-info/METADATA
xml_to_df-0.0.6.dist-info/WHEEL
xml_to_df-0.0.6.dist-info/top_level.txt
xml_to_df-0.0.6.dist-info/RECORD
