Metadata-Version: 2.1
Name: xml-to-df
Version: 0.0.6
Summary: Package to convert xml to Pandas dataframe (flattens each and every xml element to dataframe column)
Home-page: https://github.com/PraveenKumar-21/xml_to_df
Author: Praveen Kumar B
Author-email: bpraveenkumar21@gmail.com
License: UNKNOWN
Keywords: XML to Pandas Dataframe,XML to CSV,Flatten XML to DF,XML to Pandas DF
Platform: UNKNOWN
Classifier: Programming Language :: Python :: 3
Classifier: License :: OSI Approved :: MIT License
Classifier: Operating System :: OS Independent
Requires-Python: >=3.6
Requires-Dist: pandas
